test_auto_publish_lib_unique2/__init__.py
test_auto_publish_lib_unique2/get_info.py
test_auto_publish_lib_unique2-0.1.0.dist-info/METADATA
test_auto_publish_lib_unique2-0.1.0.dist-info/WHEEL
test_auto_publish_lib_unique2-0.1.0.dist-info/top_level.txt
test_auto_publish_lib_unique2-0.1.0.dist-info/RECORD
